[
  {
    "id": "spot-mr0703kd-qqelvp",
    "createdAt": "2026-06-30T05:14:57.062Z",
    "updatedAt": "2026-06-30T05:17:21.505Z",
    "title": {
      "ja": "このポストは、 どこに繋がっているのだろう。",
      "en": "このポストは、 どこに繋がっているのだろう。",
      "ko": "このポストは、 どこに繋がっているのだろう。",
      "zh": "このポストは、 どこに繋がっているのだろう。"
    },
    "description": {
      "ja": "このポストは、\nどこに繋がっているのだろう。\nWhere\ndoes this postbox lead?\n\n七尾市役所【Nanao City Hall】\nNanao, Noto Peninsula, Japan\n\n37°02’34.5”N 136°58’03.2”E\n\nArchive 012\n#MetaphysicalNoto\n#InspiredByMetaphysicalArt\n#NanaoCity\n#NotoNoOtoMuseum",
      "en": "このポストは、\nどこに繋がっているのだろう。\nWhere\ndoes this postbox lead?\n\n七尾市役所【Nanao City Hall】\nNanao, Noto Peninsula, Japan\n\n37°02’34.5”N 136°58’03.2”E\n\nArchive 012\n#MetaphysicalNoto\n#InspiredByMetaphysicalArt\n#NanaoCity\n#NotoNoOtoMuseum",
      "ko": "このポストは、\nどこに繋がっているのだろう。\nWhere\ndoes this postbox lead?\n\n나나오시役所【나나오시 City Hall】\n나나오시, Noto Peninsula, Japan\n\n37°02’34.5”N 136°58’03.2”E\n\nArchive 012\n#MetaphysicalNoto\n#InspiredByMetaphysicalArt\n#나나오시City\n#NotoNoOtoMuseum",
      "zh": "このポストは、\nどこに繋がっているのだろう。\nWhere\ndoes this postbox lead?\n\n七尾市市役所【七尾市 City Hall】\n七尾市, Noto Peninsula, Japan\n\n37°02’34.5”N 136°58’03.2”E\n\nArchive 012\n#MetaphysicalNoto\n#InspiredByMetaphysicalArt\n#七尾市City\n#NotoNoOtoMuseum"
    },
    "municipality": {
      "ja": "七尾市",
      "en": "Nanao",
      "ko": "나나오시",
      "zh": "七尾市"
    },
    "group": "七尾市",
    "locationText": "37°02’34.5”N 136°58’03.2”E",
    "lat": 0,
    "lng": 0,
    "photos": [
      {
        "src": "https://raw.githubusercontent.com/tmgddjtt57-collab/notomap/main/media/spots/1782796495188-spot-mr0703kd-qqelvp-12-line-album-20260630-260630-16.jpg?v=1782796497062",
        "alt": "LINE_ALBUM_20260630_260630_16.jpg",
        "path": "media/spots/1782796495188-spot-mr0703kd-qqelvp-12-line-album-20260630-260630-16.jpg"
      }
    ]
  },
  {
    "id": "spot-mr0706ek-t6wzb9",
    "createdAt": "2026-06-30T05:15:00.957Z",
    "updatedAt": "2026-06-30T05:15:00.957Z",
    "title": {
      "ja": "夕暮れの潮騒に、 古の記憶が残っている。",
      "en": "夕暮れの潮騒に、 古の記憶が残っている。",
      "ko": "夕暮れの潮騒に、 古の記憶が残っている。",
      "zh": "夕暮れの潮騒に、 古の記憶が残っている。"
    },
    "description": {
      "ja": "夕暮れの潮騒に、\n古の記憶が残っている。\nWithin the evening tide,\nancient memories\nstill remain.\n\nボラ待ち櫓\n【Bora-machi Yagura】\nAnamizu, Noto Peninsula, Japan\n\n37°11'25.4\"N 136°54'19.4\"E\n\nArchive 014\n#SymbolismNoto\n#InspiredByGustavKlimt\n#AnamizuTown\n#NotoNoOtoMuseum",
      "en": "夕暮れの潮騒に、\n古の記憶が残っている。\nWithin the evening tide,\nancient memories\nstill remain.\n\nボラ待ち櫓\n【Bora-machi Yagura】\nAnamizu, Noto Peninsula, Japan\n\n37°11'25.4\"N 136°54'19.4\"E\n\nArchive 014\n#SymbolismNoto\n#InspiredByGustavKlimt\n#AnamizuTown\n#NotoNoOtoMuseum",
      "ko": "夕暮れの潮騒に、\n古の記憶が残っている。\nWithin the evening tide,\nancient memories\nstill remain.\n\nボラ待ち櫓\n【Bora-machi Yagura】\n아나미즈마치, Noto Peninsula, Japan\n\n37°11'25.4\"N 136°54'19.4\"E\n\nArchive 014\n#SymbolismNoto\n#InspiredByGustavKlimt\n#아나미즈마치Town\n#NotoNoOtoMuseum",
      "zh": "夕暮れの潮騒に、\n古の記憶が残っている。\nWithin the evening tide,\nancient memories\nstill remain.\n\nボラ待ち櫓\n【Bora-machi Yagura】\n穴水町, Noto Peninsula, Japan\n\n37°11'25.4\"N 136°54'19.4\"E\n\nArchive 014\n#SymbolismNoto\n#InspiredByGustavKlimt\n#穴水町Town\n#NotoNoOtoMuseum"
    },
    "municipality": {
      "ja": "穴水町",
      "en": "Anamizu",
      "ko": "아나미즈마치",
      "zh": "穴水町"
    },
    "group": "穴水町",
    "locationText": "37°11'25.4\"N 136°54'19.4\"E",
    "lat": 37.19038888888888,
    "lng": 136.9053888888889,
    "photos": [
      {
        "src": "https://raw.githubusercontent.com/tmgddjtt57-collab/notomap/main/media/spots/1782796498869-spot-mr0706ek-t6wzb9-14-line-album-20260630-260630-18.jpg?v=1782796500957",
        "alt": "LINE_ALBUM_20260630_260630_18.jpg",
        "path": "media/spots/1782796498869-spot-mr0706ek-t6wzb9-14-line-album-20260630-260630-18.jpg"
      }
    ]
  },
  {
    "id": "spot-mr07052e-saerlg",
    "createdAt": "2026-06-30T05:14:58.796Z",
    "updatedAt": "2026-06-30T05:14:58.796Z",
    "title": {
      "ja": "役目を終えた列車が、 静かに夜へと沈んでいく。",
      "en": "役目を終えた列車が、 静かに夜へと沈んでいく。",
      "ko": "役目を終えた列車が、 静かに夜へと沈んでいく。",
      "zh": "役目を終えた列車が、 静かに夜へと沈んでいく。"
    },
    "description": {
      "ja": "役目を終えた列車が、\n静かに夜へと沈んでいく。\nThe train, having finished\nits role,\nsinks into the night.\n\n穴水駅【Anamizu Station】\nAnamizu, Noto Peninsula, Japan\n\n37°13’40.6”N 136°54’17.3”E\n\nArchive 013\n#ModernismNoto\n#InspiredByEdwardHopper\n#AnamizuTown\n#NotoNoOtoMuseum",
      "en": "役目を終えた列車が、\n静かに夜へと沈んでいく。\nThe train, having finished\nits role,\nsinks into the night.\n\n穴水駅【Anamizu Station】\nAnamizu, Noto Peninsula, Japan\n\n37°13’40.6”N 136°54’17.3”E\n\nArchive 013\n#ModernismNoto\n#InspiredByEdwardHopper\n#AnamizuTown\n#NotoNoOtoMuseum",
      "ko": "役目を終えた列車が、\n静かに夜へと沈んでいく。\nThe train, having finished\nits role,\nsinks into the night.\n\n아나미즈마치駅【아나미즈마치 Station】\n아나미즈마치, Noto Peninsula, Japan\n\n37°13’40.6”N 136°54’17.3”E\n\nArchive 013\n#ModernismNoto\n#InspiredByEdwardHopper\n#아나미즈마치Town\n#NotoNoOtoMuseum",
      "zh": "役目を終えた列車が、\n静かに夜へと沈んでいく。\nThe train, having finished\nits role,\nsinks into the night.\n\n穴水町駅【穴水町 Station】\n穴水町, Noto Peninsula, Japan\n\n37°13’40.6”N 136°54’17.3”E\n\nArchive 013\n#ModernismNoto\n#InspiredByEdwardHopper\n#穴水町Town\n#NotoNoOtoMuseum"
    },
    "municipality": {
      "ja": "穴水町",
      "en": "Anamizu",
      "ko": "아나미즈마치",
      "zh": "穴水町"
    },
    "group": "穴水町",
    "locationText": "37°13’40.6”N 136°54’17.3”E",
    "lat": 0,
    "lng": 0,
    "photos": [
      {
        "src": "https://raw.githubusercontent.com/tmgddjtt57-collab/notomap/main/media/spots/1782796497128-spot-mr07052e-saerlg-13-line-album-20260630-260630-17.jpg?v=1782796498796",
        "alt": "LINE_ALBUM_20260630_260630_17.jpg",
        "path": "media/spots/1782796497128-spot-mr07052e-saerlg-13-line-album-20260630-260630-17.jpg"
      }
    ]
  },
  {
    "id": "spot-mr0701zi-ora9dj",
    "createdAt": "2026-06-30T05:14:55.116Z",
    "updatedAt": "2026-06-30T05:14:55.116Z",
    "title": {
      "ja": "色がうるさすぎる日は、 だいたい楽しい。",
      "en": "色がうるさすぎる日は、 だいたい楽しい。",
      "ko": "色がうるさすぎる日は、 だいたい楽しい。",
      "zh": "色がうるさすぎる日は、 だいたい楽しい。"
    },
    "description": {
      "ja": "色がうるさすぎる日は、\nだいたい楽しい。\nThe days with too many colors\nare usually\nfun.\n\n氷見市海浜植物園【Himi City Seaside Botanical Garden】\nHimi, Toyama, Japan\n\n36°50’13.5”N 137°00’18.4”E\n\nArchive 011\n#FauvismNoto\n#InspiredByFauvism\n#HimiCity\n#NotoNoOtoMuseum",
      "en": "色がうるさすぎる日は、\nだいたい楽しい。\nThe days with too many colors\nare usually\nfun.\n\n氷見市海浜植物園【Himi City Seaside Botanical Garden】\nHimi, Toyama, Japan\n\n36°50’13.5”N 137°00’18.4”E\n\nArchive 011\n#FauvismNoto\n#InspiredByFauvism\n#HimiCity\n#NotoNoOtoMuseum",
      "ko": "色がうるさすぎる日は、\nだいたい楽しい。\nThe days with too many colors\nare usually\nfun.\n\n氷見市바다浜植物園【Himi City Seaside Botanical Garden】\nHimi, Toyama, Japan\n\n36°50’13.5”N 137°00’18.4”E\n\nArchive 011\n#FauvismNoto\n#InspiredByFauvism\n#HimiCity\n#NotoNoOtoMuseum",
      "zh": "色がうるさすぎる日は、\nだいたい楽しい。\nThe days with too many colors\nare usually\nfun.\n\n氷見市海浜植物園【Himi City Seaside Botanical Garden】\nHimi, Toyama, Japan\n\n36°50’13.5”N 137°00’18.4”E\n\nArchive 011\n#FauvismNoto\n#InspiredByFauvism\n#HimiCity\n#NotoNoOtoMuseum"
    },
    "municipality": {
      "ja": "能登半島",
      "en": "Noto Peninsula",
      "ko": "노토반도",
      "zh": "能登半岛"
    },
    "group": "能登半島",
    "locationText": "36°50’13.5”N 137°00’18.4”E",
    "lat": 0,
    "lng": 0,
    "photos": [
      {
        "src": "https://raw.githubusercontent.com/tmgddjtt57-collab/notomap/main/media/spots/1782796493137-spot-mr0701zi-ora9dj-11-line-album-20260630-260630-15.jpg?v=1782796495116",
        "alt": "LINE_ALBUM_20260630_260630_15.jpg",
        "path": "media/spots/1782796493137-spot-mr0701zi-ora9dj-11-line-album-20260630-260630-15.jpg"
      }
    ]
  },
  {
    "id": "spot-mr0700hf-f5cvls",
    "createdAt": "2026-06-30T05:14:53.070Z",
    "updatedAt": "2026-06-30T05:14:53.070Z",
    "title": {
      "ja": "海へと続いていたのは、 光ではなく季節だった。",
      "en": "seaへと続いていたのは、 光ではなく季節だった。",
      "ko": "바다へと続いていたのは、 光ではなく季節だった。",
      "zh": "海へと続いていたのは、 光ではなく季節だった。"
    },
    "description": {
      "ja": "海へと続いていたのは、\n光ではなく季節だった。\nWhat stretched toward the sea\nwas not light,\nbut the season itself.\n\n白米千枚田の夕日【Sunset over Shiroyone Senmaida】\nWajima, Noto Peninsula, Japan\n\n37°25’33.3”N 137°00’01.0”E\n\nArchive 009\n#PostImpressionismNoto\n#InspiredByVanGogh\n#OuterWajima\n#NotoNoOtoMuseum",
      "en": "海へと続いていたのは、\n光ではなく季節だった。\nWhat stretched toward the sea\nwas not light,\nbut the season itself.\n\n白米千枚田の夕日【Sunset over Shiroyone Senmaida】\nWajima, Noto Peninsula, Japan\n\n37°25’33.3”N 137°00’01.0”E\n\nArchive 009\n#PostImpressionismNoto\n#InspiredByVanGogh\n#OuterWajima\n#NotoNoOtoMuseum",
      "ko": "바다へと続いていたのは、\n光ではなく季節だった。\nWhat stretched toward the sea\nwas not light,\nbut the season itself.\n\n白米千枚田の夕日【Sunset over Shiroyone Senmaida】\n와지마시, Noto Peninsula, Japan\n\n37°25’33.3”N 137°00’01.0”E\n\nArchive 009\n#PostImpressionismNoto\n#InspiredByVanGogh\n#Outer와지마시\n#NotoNoOtoMuseum",
      "zh": "海へと続いていたのは、\n光ではなく季節だった。\nWhat stretched toward the sea\nwas not light,\nbut the season itself.\n\n白米千枚田の夕日【Sunset over Shiroyone Senmaida】\n轮岛市, Noto Peninsula, Japan\n\n37°25’33.3”N 137°00’01.0”E\n\nArchive 009\n#PostImpressionismNoto\n#InspiredByVanGogh\n#Outer轮岛市\n#NotoNoOtoMuseum"
    },
    "municipality": {
      "ja": "輪島市",
      "en": "Wajima",
      "ko": "와지마시",
      "zh": "轮岛市"
    },
    "group": "輪島市",
    "locationText": "37°25’33.3”N 137°00’01.0”E",
    "lat": 0,
    "lng": 0,
    "photos": [
      {
        "src": "https://raw.githubusercontent.com/tmgddjtt57-collab/notomap/main/media/spots/1782796491194-spot-mr0700hf-f5cvls-10-line-album-20260630-260630-14.jpg?v=1782796493070",
        "alt": "LINE_ALBUM_20260630_260630_14.jpg",
        "path": "media/spots/1782796491194-spot-mr0700hf-f5cvls-10-line-album-20260630-260630-14.jpg"
      }
    ]
  },
  {
    "id": "spot-mr06zz2a-s15z6p",
    "createdAt": "2026-06-30T05:14:51.122Z",
    "updatedAt": "2026-06-30T05:14:51.122Z",
    "title": {
      "ja": "海の上に、 闇が座っていた。",
      "en": "seaの上に、 闇が座っていた。",
      "ko": "바다の上に、 闇が座っていた。",
      "zh": "海の上に、 闇が座っていた。"
    },
    "description": {
      "ja": "海の上に、\n闇が座っていた。\nDarkness\nsat upon the sea.\n\n巌門【Rock Gate】\nShika, Noto Peninsula, Japan\n\n37°05’38.1”N 136°43’37.4”E\n\nArchive19\n#SymbolismNoto\n#InspiredByArnoldBocklin\n#InspiredByPaulGauguin\n#ShikaTown\n#NotoNoOtoMuseum",
      "en": "海の上に、\n闇が座っていた。\nDarkness\nsat upon the sea.\n\n巌門【Rock Gate】\nShika, Noto Peninsula, Japan\n\n37°05’38.1”N 136°43’37.4”E\n\nArchive19\n#SymbolismNoto\n#InspiredByArnoldBocklin\n#InspiredByPaulGauguin\n#ShikaTown\n#NotoNoOtoMuseum",
      "ko": "바다の上に、\n闇が座っていた。\nDarkness\nsat upon the sea.\n\n巌門【Rock Gate】\n시카마치, Noto Peninsula, Japan\n\n37°05’38.1”N 136°43’37.4”E\n\nArchive19\n#SymbolismNoto\n#InspiredByArnoldBocklin\n#InspiredByPaulGauguin\n#시카마치Town\n#NotoNoOtoMuseum",
      "zh": "海の上に、\n闇が座っていた。\nDarkness\nsat upon the sea.\n\n巌門【Rock Gate】\n志贺町, Noto Peninsula, Japan\n\n37°05’38.1”N 136°43’37.4”E\n\nArchive19\n#SymbolismNoto\n#InspiredByArnoldBocklin\n#InspiredByPaulGauguin\n#志贺町Town\n#NotoNoOtoMuseum"
    },
    "municipality": {
      "ja": "志賀町",
      "en": "Shika",
      "ko": "시카마치",
      "zh": "志贺町"
    },
    "group": "志賀町",
    "locationText": "37°05’38.1”N 136°43’37.4”E",
    "lat": 0,
    "lng": 0,
    "photos": [
      {
        "src": "https://raw.githubusercontent.com/tmgddjtt57-collab/notomap/main/media/spots/1782796489359-spot-mr06zz2a-s15z6p-9-line-album-20260630-260630-25.jpg?v=1782796491122",
        "alt": "LINE_ALBUM_20260630_260630_25.jpg",
        "path": "media/spots/1782796489359-spot-mr06zz2a-s15z6p-9-line-album-20260630-260630-25.jpg"
      }
    ]
  },
  {
    "id": "spot-mr06zxkq-ldd46o",
    "createdAt": "2026-06-30T05:14:49.281Z",
    "updatedAt": "2026-06-30T05:14:49.281Z",
    "title": {
      "ja": "海の上に、 闇が座っていた。",
      "en": "seaの上に、 闇が座っていた。",
      "ko": "바다の上に、 闇が座っていた。",
      "zh": "海の上に、 闇が座っていた。"
    },
    "description": {
      "ja": "海の上に、\n闇が座っていた。\nDarkness\nsat upon the sea.\n\n巌門【Rock Gate】\nShika, Noto Peninsula, Japan\n\n37°05’38.1”N 136°43’37.4”E\n\nArchive19\n#SymbolismNoto\n#InspiredByArnoldBocklin\n#InspiredByPaulGauguin\n#ShikaTown\n#NotoNoOtoMuseum",
      "en": "海の上に、\n闇が座っていた。\nDarkness\nsat upon the sea.\n\n巌門【Rock Gate】\nShika, Noto Peninsula, Japan\n\n37°05’38.1”N 136°43’37.4”E\n\nArchive19\n#SymbolismNoto\n#InspiredByArnoldBocklin\n#InspiredByPaulGauguin\n#ShikaTown\n#NotoNoOtoMuseum",
      "ko": "바다の上に、\n闇が座っていた。\nDarkness\nsat upon the sea.\n\n巌門【Rock Gate】\n시카마치, Noto Peninsula, Japan\n\n37°05’38.1”N 136°43’37.4”E\n\nArchive19\n#SymbolismNoto\n#InspiredByArnoldBocklin\n#InspiredByPaulGauguin\n#시카마치Town\n#NotoNoOtoMuseum",
      "zh": "海の上に、\n闇が座っていた。\nDarkness\nsat upon the sea.\n\n巌門【Rock Gate】\n志贺町, Noto Peninsula, Japan\n\n37°05’38.1”N 136°43’37.4”E\n\nArchive19\n#SymbolismNoto\n#InspiredByArnoldBocklin\n#InspiredByPaulGauguin\n#志贺町Town\n#NotoNoOtoMuseum"
    },
    "municipality": {
      "ja": "志賀町",
      "en": "Shika",
      "ko": "시카마치",
      "zh": "志贺町"
    },
    "group": "志賀町",
    "locationText": "37°05’38.1”N 136°43’37.4”E",
    "lat": 0,
    "lng": 0,
    "photos": [
      {
        "src": "https://raw.githubusercontent.com/tmgddjtt57-collab/notomap/main/media/spots/1782796487426-spot-mr06zxkq-ldd46o-8-line-album-20260630-260630-24.jpg?v=1782796489281",
        "alt": "LINE_ALBUM_20260630_260630_24.jpg",
        "path": "media/spots/1782796487426-spot-mr06zxkq-ldd46o-8-line-album-20260630-260630-24.jpg"
      }
    ]
  },
  {
    "id": "spot-mr06zvw7-imvdqd",
    "createdAt": "2026-06-30T05:14:47.354Z",
    "updatedAt": "2026-06-30T05:14:47.354Z",
    "title": {
      "ja": "杉の奥に、 雪が残っていた。",
      "en": "杉の奥に、 雪が残っていた。",
      "ko": "杉の奥に、 雪が残っていた。",
      "zh": "杉の奥に、 雪が残っていた。"
    },
    "description": {
      "ja": "杉の奥に、\n雪が残っていた。\nDeep within the cedars,\nsnow remained.\n\n来迎寺【Raigōji Temple】\nAnamizu, Noto Peninsula, Japan\n\n37°13'46.0\"N 136°53'45.8\"E\n\nArchive 018\n#SymbolismNoto\n#InspiredByHigashiyamaKaii\n#InspiredByRyuzaburoUmehara\n#AnamizuTown\n#NotoNoOtoMuseum",
      "en": "杉の奥に、\n雪が残っていた。\nDeep within the cedars,\nsnow remained.\n\n来迎寺【Raigōji Temple】\nAnamizu, Noto Peninsula, Japan\n\n37°13'46.0\"N 136°53'45.8\"E\n\nArchive 018\n#SymbolismNoto\n#InspiredByHigashiyamaKaii\n#InspiredByRyuzaburoUmehara\n#AnamizuTown\n#NotoNoOtoMuseum",
      "ko": "杉の奥に、\n雪が残っていた。\nDeep within the cedars,\nsnow remained.\n\n来迎寺【Raigōji Temple】\n아나미즈마치, Noto Peninsula, Japan\n\n37°13'46.0\"N 136°53'45.8\"E\n\nArchive 018\n#SymbolismNoto\n#InspiredByHigashiyamaKaii\n#InspiredByRyuzaburoUmehara\n#아나미즈마치Town\n#NotoNoOtoMuseum",
      "zh": "杉の奥に、\n雪が残っていた。\nDeep within the cedars,\nsnow remained.\n\n来迎寺【Raigōji Temple】\n穴水町, Noto Peninsula, Japan\n\n37°13'46.0\"N 136°53'45.8\"E\n\nArchive 018\n#SymbolismNoto\n#InspiredByHigashiyamaKaii\n#InspiredByRyuzaburoUmehara\n#穴水町Town\n#NotoNoOtoMuseum"
    },
    "municipality": {
      "ja": "穴水町",
      "en": "Anamizu",
      "ko": "아나미즈마치",
      "zh": "穴水町"
    },
    "group": "穴水町",
    "locationText": "37°13'46.0\"N 136°53'45.8\"E",
    "lat": 37.22944444444445,
    "lng": 136.89605555555553,
    "photos": [
      {
        "src": "https://raw.githubusercontent.com/tmgddjtt57-collab/notomap/main/media/spots/1782796485245-spot-mr06zvw7-imvdqd-7-line-album-20260630-260630-23.jpg?v=1782796487354",
        "alt": "LINE_ALBUM_20260630_260630_23.jpg",
        "path": "media/spots/1782796485245-spot-mr06zvw7-imvdqd-7-line-album-20260630-260630-23.jpg"
      }
    ]
  },
  {
    "id": "spot-mr06zuc7-z17zvt",
    "createdAt": "2026-06-30T05:14:45.174Z",
    "updatedAt": "2026-06-30T05:14:45.174Z",
    "title": {
      "ja": "杉の奥に、 雪が残っていた。",
      "en": "杉の奥に、 雪が残っていた。",
      "ko": "杉の奥に、 雪が残っていた。",
      "zh": "杉の奥に、 雪が残っていた。"
    },
    "description": {
      "ja": "杉の奥に、\n雪が残っていた。\nDeep within the cedars,\nsnow remained.\n\n来迎寺【Raigōji Temple】\nAnamizu, Noto Peninsula, Japan\n\n37°13'46.0\"N 136°53'45.8\"E\n\nArchive 018\n#SymbolismNoto\n#InspiredByHigashiyamaKaii\n#InspiredByRyuzaburoUmehara\n#AnamizuTown\n#NotoNoOtoMuseum",
      "en": "杉の奥に、\n雪が残っていた。\nDeep within the cedars,\nsnow remained.\n\n来迎寺【Raigōji Temple】\nAnamizu, Noto Peninsula, Japan\n\n37°13'46.0\"N 136°53'45.8\"E\n\nArchive 018\n#SymbolismNoto\n#InspiredByHigashiyamaKaii\n#InspiredByRyuzaburoUmehara\n#AnamizuTown\n#NotoNoOtoMuseum",
      "ko": "杉の奥に、\n雪が残っていた。\nDeep within the cedars,\nsnow remained.\n\n来迎寺【Raigōji Temple】\n아나미즈마치, Noto Peninsula, Japan\n\n37°13'46.0\"N 136°53'45.8\"E\n\nArchive 018\n#SymbolismNoto\n#InspiredByHigashiyamaKaii\n#InspiredByRyuzaburoUmehara\n#아나미즈마치Town\n#NotoNoOtoMuseum",
      "zh": "杉の奥に、\n雪が残っていた。\nDeep within the cedars,\nsnow remained.\n\n来迎寺【Raigōji Temple】\n穴水町, Noto Peninsula, Japan\n\n37°13'46.0\"N 136°53'45.8\"E\n\nArchive 018\n#SymbolismNoto\n#InspiredByHigashiyamaKaii\n#InspiredByRyuzaburoUmehara\n#穴水町Town\n#NotoNoOtoMuseum"
    },
    "municipality": {
      "ja": "穴水町",
      "en": "Anamizu",
      "ko": "아나미즈마치",
      "zh": "穴水町"
    },
    "group": "穴水町",
    "locationText": "37°13'46.0\"N 136°53'45.8\"E",
    "lat": 37.22944444444445,
    "lng": 136.89605555555553,
    "photos": [
      {
        "src": "https://raw.githubusercontent.com/tmgddjtt57-collab/notomap/main/media/spots/1782796483242-spot-mr06zuc7-z17zvt-6-line-album-20260630-260630-22.jpg?v=1782796485174",
        "alt": "LINE_ALBUM_20260630_260630_22.jpg",
        "path": "media/spots/1782796483242-spot-mr06zuc7-z17zvt-6-line-album-20260630-260630-22.jpg"
      }
    ]
  },
  {
    "id": "spot-mr06ztd1-yf2zd8",
    "createdAt": "2026-06-30T05:14:43.159Z",
    "updatedAt": "2026-06-30T05:14:43.159Z",
    "title": {
      "ja": "――FM Sodegahama、 今日のお天気ですが、 猫だけ少し早く春休み入ってます。",
      "en": "――FM Sodegahama、 今日のお天気ですが、 猫だけ少し早くspring休み入ってます。",
      "ko": "――FM Sodegahama、 今日のお天気ですが、 猫だけ少し早く봄休み入ってます。",
      "zh": "――FM Sodegahama、 今日のお天気ですが、 猫だけ少し早く春天休み入ってます。"
    },
    "description": {
      "ja": "――FM Sodegahama、\n今日のお天気ですが、\n猫だけ少し早く春休み入ってます。\n— FM Sodegahama,\ntoday’s weather:\nthe cat has gone on spring break a little early.\n\n袖ヶ浜【Sodegahama Coast】\nWajima, Noto Peninsula, Japan\n\n37°24’09.0”N 136°53’47.8”E\n\nArchive 017\n#ModernismNoto\n#InspiredByJapanesePopCulture\n#WajimaCity\n#NotoNoOtoMuseum",
      "en": "――FM Sodegahama、\n今日のお天気ですが、\n猫だけ少し早く春休み入ってます。\n— FM Sodegahama,\ntoday’s weather:\nthe cat has gone on spring break a little early.\n\n袖ヶ浜【Sodegahama Coast】\nWajima, Noto Peninsula, Japan\n\n37°24’09.0”N 136°53’47.8”E\n\nArchive 017\n#ModernismNoto\n#InspiredByJapanesePopCulture\n#WajimaCity\n#NotoNoOtoMuseum",
      "ko": "――FM Sodegahama、\n今日のお天気ですが、\n猫だけ少し早く봄休み入ってます。\n— FM Sodegahama,\ntoday’s weather:\nthe cat has gone on spring break a little early.\n\n袖ヶ浜【Sodegahama Coast】\n와지마시, Noto Peninsula, Japan\n\n37°24’09.0”N 136°53’47.8”E\n\nArchive 017\n#ModernismNoto\n#InspiredByJapanesePopCulture\n#와지마시City\n#NotoNoOtoMuseum",
      "zh": "――FM Sodegahama、\n今日のお天気ですが、\n猫だけ少し早く春天休み入ってます。\n— FM Sodegahama,\ntoday’s weather:\nthe cat has gone on spring break a little early.\n\n袖ヶ浜【Sodegahama Coast】\n轮岛市, Noto Peninsula, Japan\n\n37°24’09.0”N 136°53’47.8”E\n\nArchive 017\n#ModernismNoto\n#InspiredByJapanesePopCulture\n#轮岛市City\n#NotoNoOtoMuseum"
    },
    "municipality": {
      "ja": "輪島市",
      "en": "Wajima",
      "ko": "와지마시",
      "zh": "轮岛市"
    },
    "group": "輪島市",
    "locationText": "37°24’09.0”N 136°53’47.8”E",
    "lat": 0,
    "lng": 0,
    "photos": [
      {
        "src": "https://raw.githubusercontent.com/tmgddjtt57-collab/notomap/main/media/spots/1782796481972-spot-mr06ztd1-yf2zd8-5-line-album-20260630-260630-21.jpg?v=1782796483159",
        "alt": "LINE_ALBUM_20260630_260630_21.jpg",
        "path": "media/spots/1782796481972-spot-mr06ztd1-yf2zd8-5-line-album-20260630-260630-21.jpg"
      }
    ]
  },
  {
    "id": "spot-mr06zrsh-bib969",
    "createdAt": "2026-06-30T05:14:41.892Z",
    "updatedAt": "2026-06-30T05:14:41.892Z",
    "title": {
      "ja": "空が、 まだ何かを覚えていた。",
      "en": "空が、 まだ何かを覚えていた。",
      "ko": "空が、 まだ何かを覚えていた。",
      "zh": "空が、 まだ何かを覚えていた。"
    },
    "description": {
      "ja": "空が、\nまだ何かを覚えていた。\nThe sky\nremembered\nsomething.\n\n輪島朝市跡【Remains of the Wajima Morning Market】\nWajima, Noto Peninsula, Japan\n\n37°23’45.0”N 136°54’03.7”E\n\nArchive 022\n#SymbolismNoto\n#InspiredByTarkovsky\n#InspiredByFranciscoGoya\n#WajimaCity\n#NotoNoOtoMuseum",
      "en": "空が、\nまだ何かを覚えていた。\nThe sky\nremembered\nsomething.\n\n輪島朝市跡【Remains of the Wajima Morning Market】\nWajima, Noto Peninsula, Japan\n\n37°23’45.0”N 136°54’03.7”E\n\nArchive 022\n#SymbolismNoto\n#InspiredByTarkovsky\n#InspiredByFranciscoGoya\n#WajimaCity\n#NotoNoOtoMuseum",
      "ko": "空が、\nまだ何かを覚えていた。\nThe sky\nremembered\nsomething.\n\n와지마시朝市跡【Remains of the 와지마시 Morning Market】\n와지마시, Noto Peninsula, Japan\n\n37°23’45.0”N 136°54’03.7”E\n\nArchive 022\n#SymbolismNoto\n#InspiredByTarkovsky\n#InspiredByFranciscoGoya\n#와지마시City\n#NotoNoOtoMuseum",
      "zh": "空が、\nまだ何かを覚えていた。\nThe sky\nremembered\nsomething.\n\n轮岛市朝市跡【Remains of the 轮岛市 Morning Market】\n轮岛市, Noto Peninsula, Japan\n\n37°23’45.0”N 136°54’03.7”E\n\nArchive 022\n#SymbolismNoto\n#InspiredByTarkovsky\n#InspiredByFranciscoGoya\n#轮岛市City\n#NotoNoOtoMuseum"
    },
    "municipality": {
      "ja": "輪島市",
      "en": "Wajima",
      "ko": "와지마시",
      "zh": "轮岛市"
    },
    "group": "輪島市",
    "locationText": "37°23’45.0”N 136°54’03.7”E",
    "lat": 0,
    "lng": 0,
    "photos": [
      {
        "src": "https://raw.githubusercontent.com/tmgddjtt57-collab/notomap/main/media/spots/1782796479936-spot-mr06zrsh-bib969-4-line-album-20260630-260630-30.jpg?v=1782796481892",
        "alt": "LINE_ALBUM_20260630_260630_30.jpg",
        "path": "media/spots/1782796479936-spot-mr06zrsh-bib969-4-line-album-20260630-260630-30.jpg"
      }
    ]
  },
  {
    "id": "spot-mr06zqed-oy5vr1",
    "createdAt": "2026-06-30T05:14:39.857Z",
    "updatedAt": "2026-06-30T05:14:39.857Z",
    "title": {
      "ja": "空が、 まだ何かを覚えていた。",
      "en": "空が、 まだ何かを覚えていた。",
      "ko": "空が、 まだ何かを覚えていた。",
      "zh": "空が、 まだ何かを覚えていた。"
    },
    "description": {
      "ja": "空が、\nまだ何かを覚えていた。\nThe sky\nremembered\nsomething.\n\n輪島朝市跡【Remains of the Wajima Morning Market】\nWajima, Noto Peninsula, Japan\n\n37°23’45.0”N 136°54’03.7”E\n\nArchive 022\n#SymbolismNoto\n#InspiredByTarkovsky\n#InspiredByFranciscoGoya\n#WajimaCity\n#NotoNoOtoMuseum",
      "en": "空が、\nまだ何かを覚えていた。\nThe sky\nremembered\nsomething.\n\n輪島朝市跡【Remains of the Wajima Morning Market】\nWajima, Noto Peninsula, Japan\n\n37°23’45.0”N 136°54’03.7”E\n\nArchive 022\n#SymbolismNoto\n#InspiredByTarkovsky\n#InspiredByFranciscoGoya\n#WajimaCity\n#NotoNoOtoMuseum",
      "ko": "空が、\nまだ何かを覚えていた。\nThe sky\nremembered\nsomething.\n\n와지마시朝市跡【Remains of the 와지마시 Morning Market】\n와지마시, Noto Peninsula, Japan\n\n37°23’45.0”N 136°54’03.7”E\n\nArchive 022\n#SymbolismNoto\n#InspiredByTarkovsky\n#InspiredByFranciscoGoya\n#와지마시City\n#NotoNoOtoMuseum",
      "zh": "空が、\nまだ何かを覚えていた。\nThe sky\nremembered\nsomething.\n\n轮岛市朝市跡【Remains of the 轮岛市 Morning Market】\n轮岛市, Noto Peninsula, Japan\n\n37°23’45.0”N 136°54’03.7”E\n\nArchive 022\n#SymbolismNoto\n#InspiredByTarkovsky\n#InspiredByFranciscoGoya\n#轮岛市City\n#NotoNoOtoMuseum"
    },
    "municipality": {
      "ja": "輪島市",
      "en": "Wajima",
      "ko": "와지마시",
      "zh": "轮岛市"
    },
    "group": "輪島市",
    "locationText": "37°23’45.0”N 136°54’03.7”E",
    "lat": 0,
    "lng": 0,
    "photos": [
      {
        "src": "https://raw.githubusercontent.com/tmgddjtt57-collab/notomap/main/media/spots/1782796478161-spot-mr06zqed-oy5vr1-3-line-album-20260630-260630-29.jpg?v=1782796479857",
        "alt": "LINE_ALBUM_20260630_260630_29.jpg",
        "path": "media/spots/1782796478161-spot-mr06zqed-oy5vr1-3-line-album-20260630-260630-29.jpg"
      }
    ]
  },
  {
    "id": "spot-mr06zosw-xhn8qi",
    "createdAt": "2026-06-30T05:14:38.052Z",
    "updatedAt": "2026-06-30T05:14:38.052Z",
    "title": {
      "ja": "山寺には、 誰にも邪魔されない祈りがある。",
      "en": "山寺には、 誰にも邪魔されない祈りがある。",
      "ko": "山寺には、 誰にも邪魔されない祈りがある。",
      "zh": "山寺には、 誰にも邪魔されない祈りがある。"
    },
    "description": {
      "ja": "山寺には、\n誰にも邪魔されない祈りがある。\nIn the mountain temple,\nthere is a prayer\nno one can disturb.\n\n本行寺【Hongyoji Temple】\nNanao, Noto Peninsula, Japan\n\n37°03’00.8”N 136°57’14.9”E\n\nArchive 021\n#JapaneseWoodblockPrintsNoto\n#InspiredByShikoMunakata\n#InspiredByUnichiHiratsuka\n#NanaoCity\n#NotoNoOtoMuseum",
      "en": "山寺には、\n誰にも邪魔されない祈りがある。\nIn the mountain temple,\nthere is a prayer\nno one can disturb.\n\n本行寺【Hongyoji Temple】\nNanao, Noto Peninsula, Japan\n\n37°03’00.8”N 136°57’14.9”E\n\nArchive 021\n#JapaneseWoodblockPrintsNoto\n#InspiredByShikoMunakata\n#InspiredByUnichiHiratsuka\n#NanaoCity\n#NotoNoOtoMuseum",
      "ko": "山寺には、\n誰にも邪魔されない祈りがある。\nIn the mountain temple,\nthere is a prayer\nno one can disturb.\n\n本行寺【Hongyoji Temple】\n나나오시, Noto Peninsula, Japan\n\n37°03’00.8”N 136°57’14.9”E\n\nArchive 021\n#JapaneseWoodblockPrintsNoto\n#InspiredByShikoMunakata\n#InspiredByUnichiHiratsuka\n#나나오시City\n#NotoNoOtoMuseum",
      "zh": "山寺には、\n誰にも邪魔されない祈りがある。\nIn the mountain temple,\nthere is a prayer\nno one can disturb.\n\n本行寺【Hongyoji Temple】\n七尾市, Noto Peninsula, Japan\n\n37°03’00.8”N 136°57’14.9”E\n\nArchive 021\n#JapaneseWoodblockPrintsNoto\n#InspiredByShikoMunakata\n#InspiredByUnichiHiratsuka\n#七尾市City\n#NotoNoOtoMuseum"
    },
    "municipality": {
      "ja": "七尾市",
      "en": "Nanao",
      "ko": "나나오시",
      "zh": "七尾市"
    },
    "group": "七尾市",
    "locationText": "37°03’00.8”N 136°57’14.9”E",
    "lat": 0,
    "lng": 0,
    "photos": [
      {
        "src": "https://raw.githubusercontent.com/tmgddjtt57-collab/notomap/main/media/spots/1782796476064-spot-mr06zosw-xhn8qi-2-line-album-20260630-260630-28.jpg?v=1782796478052",
        "alt": "LINE_ALBUM_20260630_260630_28.jpg",
        "path": "media/spots/1782796476064-spot-mr06zosw-xhn8qi-2-line-album-20260630-260630-28.jpg"
      }
    ]
  },
  {
    "id": "spot-mr06zn1e-ozt2ao",
    "createdAt": "2026-06-30T05:14:35.982Z",
    "updatedAt": "2026-06-30T05:14:35.982Z",
    "title": {
      "ja": "山寺には、 誰にも邪魔されない祈りがある。",
      "en": "山寺には、 誰にも邪魔されない祈りがある。",
      "ko": "山寺には、 誰にも邪魔されない祈りがある。",
      "zh": "山寺には、 誰にも邪魔されない祈りがある。"
    },
    "description": {
      "ja": "山寺には、\n誰にも邪魔されない祈りがある。\nIn the mountain temple,\nthere is a prayer\nno one can disturb.\n\n本行寺【Hongyoji Temple】\nNanao, Noto Peninsula, Japan\n\n37°03’00.8”N 136°57’14.9”E\n\nArchive 021\n#JapaneseWoodblockPrintsNoto\n#InspiredByShikoMunakata\n#InspiredByUnichiHiratsuka\n#NanaoCity\n#NotoNoOtoMuseum",
      "en": "山寺には、\n誰にも邪魔されない祈りがある。\nIn the mountain temple,\nthere is a prayer\nno one can disturb.\n\n本行寺【Hongyoji Temple】\nNanao, Noto Peninsula, Japan\n\n37°03’00.8”N 136°57’14.9”E\n\nArchive 021\n#JapaneseWoodblockPrintsNoto\n#InspiredByShikoMunakata\n#InspiredByUnichiHiratsuka\n#NanaoCity\n#NotoNoOtoMuseum",
      "ko": "山寺には、\n誰にも邪魔されない祈りがある。\nIn the mountain temple,\nthere is a prayer\nno one can disturb.\n\n本行寺【Hongyoji Temple】\n나나오시, Noto Peninsula, Japan\n\n37°03’00.8”N 136°57’14.9”E\n\nArchive 021\n#JapaneseWoodblockPrintsNoto\n#InspiredByShikoMunakata\n#InspiredByUnichiHiratsuka\n#나나오시City\n#NotoNoOtoMuseum",
      "zh": "山寺には、\n誰にも邪魔されない祈りがある。\nIn the mountain temple,\nthere is a prayer\nno one can disturb.\n\n本行寺【Hongyoji Temple】\n七尾市, Noto Peninsula, Japan\n\n37°03’00.8”N 136°57’14.9”E\n\nArchive 021\n#JapaneseWoodblockPrintsNoto\n#InspiredByShikoMunakata\n#InspiredByUnichiHiratsuka\n#七尾市City\n#NotoNoOtoMuseum"
    },
    "municipality": {
      "ja": "七尾市",
      "en": "Nanao",
      "ko": "나나오시",
      "zh": "七尾市"
    },
    "group": "七尾市",
    "locationText": "37°03’00.8”N 136°57’14.9”E",
    "lat": 0,
    "lng": 0,
    "photos": [
      {
        "src": "https://raw.githubusercontent.com/tmgddjtt57-collab/notomap/main/media/spots/1782796473790-spot-mr06zn1e-ozt2ao-1-line-album-20260630-260630-27.jpg?v=1782796475982",
        "alt": "LINE_ALBUM_20260630_260630_27.jpg",
        "path": "media/spots/1782796473790-spot-mr06zn1e-ozt2ao-1-line-album-20260630-260630-27.jpg"
      }
    ]
  },
  {
    "id": "spot-mr06m2nh-2an11c",
    "createdAt": "2026-06-30T05:04:02.749Z",
    "updatedAt": "2026-06-30T05:04:02.749Z",
    "title": {
      "ja": "ベニカナメモチが、 道端で、 昼寝をしていた。",
      "en": "ベニカナメモチが、 道端で、 昼寝をしていた。",
      "ko": "ベニカナメモチが、 道端で、 昼寝をしていた。",
      "zh": "ベニカナメモチが、 道端で、 昼寝をしていた。"
    },
    "description": {
      "ja": "ベニカナメモチが、\n道端で、\n昼寝をしていた。\nBenikanamemochi\nwas taking a nap\nby the roadside.\n\nベニカナメモチ【Japanese Red-tip Photinia】\nNoto Town, Noto Peninsula, Japan\n\n37°15'54.9\"N 137°05'26.6\"E\n\nArchive 005\n#PostImpressionismNoto\n#InspiredByCezanne\n#InspiredByTiffanyGlass\n#NotoTown\n#NotoNoOtoMuseum",
      "en": "ベニカナメモチが、\n道端で、\n昼寝をしていた。\nBenikanamemochi\nwas taking a nap\nby the roadside.\n\nベニカナメモチ【Japanese Red-tip Photinia】\nNoto Town, Noto Peninsula, Japan\n\n37°15'54.9\"N 137°05'26.6\"E\n\nArchive 005\n#PostImpressionismNoto\n#InspiredByCezanne\n#InspiredByTiffanyGlass\n#NotoTown\n#NotoNoOtoMuseum",
      "ko": "ベニカナメモチが、\n道端で、\n昼寝をしていた。\nBenikanamemochi\nwas taking a nap\nby the roadside.\n\nベニカナメモチ【Japanese Red-tip Photinia】\n노토마치, Noto Peninsula, Japan\n\n37°15'54.9\"N 137°05'26.6\"E\n\nArchive 005\n#PostImpressionismNoto\n#InspiredByCezanne\n#InspiredByTiffanyGlass\n#NotoTown\n#NotoNoOtoMuseum",
      "zh": "ベニカナメモチが、\n道端で、\n昼寝をしていた。\nBenikanamemochi\nwas taking a nap\nby the roadside.\n\nベニカナメモチ【Japanese Red-tip Photinia】\n能登町, Noto Peninsula, Japan\n\n37°15'54.9\"N 137°05'26.6\"E\n\nArchive 005\n#PostImpressionismNoto\n#InspiredByCezanne\n#InspiredByTiffanyGlass\n#NotoTown\n#NotoNoOtoMuseum"
    },
    "municipality": {
      "ja": "能登町",
      "en": "Noto Town",
      "ko": "노토마치",
      "zh": "能登町"
    },
    "group": "能登町",
    "locationText": "37°15'54.9\"N 137°05'26.6\"E",
    "lat": 37.26525,
    "lng": 137.09072222222224,
    "photos": [
      {
        "src": "https://raw.githubusercontent.com/tmgddjtt57-collab/notomap/main/media/spots/1782795840829-spot-mr06m2nh-2an11c-10-line-album-20260630-260630-4.jpg?v=1782795842749",
        "alt": "LINE_ALBUM_20260630_260630_4.jpg",
        "path": "media/spots/1782795840829-spot-mr06m2nh-2an11c-10-line-album-20260630-260630-4.jpg"
      }
    ]
  },
  {
    "id": "spot-mr06m15l-08xr1q",
    "createdAt": "2026-06-30T05:04:00.749Z",
    "updatedAt": "2026-06-30T05:04:00.749Z",
    "title": {
      "ja": "面と点が、 押し寄せる",
      "en": "面と点が、 押し寄せる",
      "ko": "面と点が、 押し寄せる",
      "zh": "面と点が、 押し寄せる"
    },
    "description": {
      "ja": "面と点が、\n押し寄せる。\nPlanes and dots\ncome rushing in.\n\n百楽荘貸切風呂 【【Private Bath at Noto Hyakurakusou】\nNoto Town, Noto Peninsula, Japan\n\n37°18'36.4\"N 137°13'57.1\"E\n\nArchive 004\n#AvantGardeNoto\n#InspiredByPicasso\n#InspiredByYayoiKusama\n#NotoTown\n#NotoNoOtoMuseum",
      "en": "面と点が、\n押し寄せる。\nPlanes and dots\ncome rushing in.\n\n百楽荘貸切風呂 【【Private Bath at Noto Hyakurakusou】\nNoto Town, Noto Peninsula, Japan\n\n37°18'36.4\"N 137°13'57.1\"E\n\nArchive 004\n#AvantGardeNoto\n#InspiredByPicasso\n#InspiredByYayoiKusama\n#NotoTown\n#NotoNoOtoMuseum",
      "ko": "面と点が、\n押し寄せる。\nPlanes and dots\ncome rushing in.\n\n百楽荘貸切風呂 【【Private Bath at Noto Hyakurakusou】\n노토마치, Noto Peninsula, Japan\n\n37°18'36.4\"N 137°13'57.1\"E\n\nArchive 004\n#AvantGardeNoto\n#InspiredByPicasso\n#InspiredByYayoiKusama\n#NotoTown\n#NotoNoOtoMuseum",
      "zh": "面と点が、\n押し寄せる。\nPlanes and dots\ncome rushing in.\n\n百楽荘貸切風呂 【【Private Bath at Noto Hyakurakusou】\n能登町, Noto Peninsula, Japan\n\n37°18'36.4\"N 137°13'57.1\"E\n\nArchive 004\n#AvantGardeNoto\n#InspiredByPicasso\n#InspiredByYayoiKusama\n#NotoTown\n#NotoNoOtoMuseum"
    },
    "municipality": {
      "ja": "能登町",
      "en": "Noto Town",
      "ko": "노토마치",
      "zh": "能登町"
    },
    "group": "能登町",
    "locationText": "37°18'36.4\"N 137°13'57.1\"E",
    "lat": 37.310111111111105,
    "lng": 137.2325277777778,
    "photos": [
      {
        "src": "https://raw.githubusercontent.com/tmgddjtt57-collab/notomap/main/media/spots/1782795838882-spot-mr06m15l-08xr1q-9-line-album-20260630-260630-3.jpg?v=1782795840749",
        "alt": "LINE_ALBUM_20260630_260630_3.jpg",
        "path": "media/spots/1782795838882-spot-mr06m15l-08xr1q-9-line-album-20260630-260630-3.jpg"
      }
    ]
  },
  {
    "id": "spot-mr06lzi6-qn5uzy",
    "createdAt": "2026-06-30T05:03:58.809Z",
    "updatedAt": "2026-06-30T05:03:58.809Z",
    "title": {
      "ja": "春は静かに、 昔の時間へと戻っていく。",
      "en": "springは静かに、 昔の時間へと戻っていく。",
      "ko": "봄は静かに、 昔の時間へと戻っていく。",
      "zh": "春天は静かに、 昔の時間へと戻っていく。"
    },
    "description": {
      "ja": "春は静かに、\n昔の時間へと戻っていく。\nSpring quietly\ndrifts back\ntoward an older time.\n\n神和住の枝垂れ桜【The Weeping Cherry Tree in Kamiwasumi】\nNoto Town, Noto Peninsula, Japan\n\n37°20'27.4\"N 137°03'47.8\"E\n\nArchive 008\n#ShinHangaNoto\n#InspiredByShoenUemura\n#InspiredByKawaseHasui\n#NotoTown\n#NotoNoOtoMuseum",
      "en": "春は静かに、\n昔の時間へと戻っていく。\nSpring quietly\ndrifts back\ntoward an older time.\n\n神和住の枝垂れ桜【The Weeping Cherry Tree in Kamiwasumi】\nNoto Town, Noto Peninsula, Japan\n\n37°20'27.4\"N 137°03'47.8\"E\n\nArchive 008\n#ShinHangaNoto\n#InspiredByShoenUemura\n#InspiredByKawaseHasui\n#NotoTown\n#NotoNoOtoMuseum",
      "ko": "봄は静かに、\n昔の時間へと戻っていく。\nSpring quietly\ndrifts back\ntoward an older time.\n\n神和住の枝垂れ桜【The Weeping Cherry Tree in Kamiwasumi】\n노토마치, Noto Peninsula, Japan\n\n37°20'27.4\"N 137°03'47.8\"E\n\nArchive 008\n#ShinHangaNoto\n#InspiredByShoenUemura\n#InspiredByKawaseHasui\n#NotoTown\n#NotoNoOtoMuseum",
      "zh": "春天は静かに、\n昔の時間へと戻っていく。\nSpring quietly\ndrifts back\ntoward an older time.\n\n神和住の枝垂れ桜【The Weeping Cherry Tree in Kamiwasumi】\n能登町, Noto Peninsula, Japan\n\n37°20'27.4\"N 137°03'47.8\"E\n\nArchive 008\n#ShinHangaNoto\n#InspiredByShoenUemura\n#InspiredByKawaseHasui\n#NotoTown\n#NotoNoOtoMuseum"
    },
    "municipality": {
      "ja": "能登町",
      "en": "Noto Town",
      "ko": "노토마치",
      "zh": "能登町"
    },
    "group": "能登町",
    "locationText": "37°20'27.4\"N 137°03'47.8\"E",
    "lat": 37.340944444444446,
    "lng": 137.06327777777778,
    "photos": [
      {
        "src": "https://raw.githubusercontent.com/tmgddjtt57-collab/notomap/main/media/spots/1782795836733-spot-mr06lzi6-qn5uzy-8-line-album-20260630-260630-13.jpg?v=1782795838809",
        "alt": "LINE_ALBUM_20260630_260630_13.jpg",
        "path": "media/spots/1782795836733-spot-mr06lzi6-qn5uzy-8-line-album-20260630-260630-13.jpg"
      }
    ]
  },
  {
    "id": "spot-mr06lwtd-o3el8m",
    "createdAt": "2026-06-30T05:03:56.669Z",
    "updatedAt": "2026-06-30T05:03:56.669Z",
    "title": {
      "ja": "ベニカナメモチが、 道端で、 昼寝をしていた。",
      "en": "ベニカナメモチが、 道端で、 昼寝をしていた。",
      "ko": "ベニカナメモチが、 道端で、 昼寝をしていた。",
      "zh": "ベニカナメモチが、 道端で、 昼寝をしていた。"
    },
    "description": {
      "ja": "ベニカナメモチが、\n道端で、\n昼寝をしていた。\nBenikanamemochi\nwas taking a nap\nby the roadside.\n\nベニカナメモチ【Japanese Red-tip Photinia】\nNoto Town, Noto Peninsula, Japan\n\n37°15'54.9\"N 137°05'26.6\"E\n\nArchive 005\n#PostImpressionismNoto\n#InspiredByCezanne\n#InspiredByTiffanyGlass\n#NotoTown\n#NotoNoOtoMuseum",
      "en": "ベニカナメモチが、\n道端で、\n昼寝をしていた。\nBenikanamemochi\nwas taking a nap\nby the roadside.\n\nベニカナメモチ【Japanese Red-tip Photinia】\nNoto Town, Noto Peninsula, Japan\n\n37°15'54.9\"N 137°05'26.6\"E\n\nArchive 005\n#PostImpressionismNoto\n#InspiredByCezanne\n#InspiredByTiffanyGlass\n#NotoTown\n#NotoNoOtoMuseum",
      "ko": "ベニカナメモチが、\n道端で、\n昼寝をしていた。\nBenikanamemochi\nwas taking a nap\nby the roadside.\n\nベニカナメモチ【Japanese Red-tip Photinia】\n노토마치, Noto Peninsula, Japan\n\n37°15'54.9\"N 137°05'26.6\"E\n\nArchive 005\n#PostImpressionismNoto\n#InspiredByCezanne\n#InspiredByTiffanyGlass\n#NotoTown\n#NotoNoOtoMuseum",
      "zh": "ベニカナメモチが、\n道端で、\n昼寝をしていた。\nBenikanamemochi\nwas taking a nap\nby the roadside.\n\nベニカナメモチ【Japanese Red-tip Photinia】\n能登町, Noto Peninsula, Japan\n\n37°15'54.9\"N 137°05'26.6\"E\n\nArchive 005\n#PostImpressionismNoto\n#InspiredByCezanne\n#InspiredByTiffanyGlass\n#NotoTown\n#NotoNoOtoMuseum"
    },
    "municipality": {
      "ja": "能登町",
      "en": "Noto Town",
      "ko": "노토마치",
      "zh": "能登町"
    },
    "group": "能登町",
    "locationText": "37°15'54.9\"N 137°05'26.6\"E",
    "lat": 37.26525,
    "lng": 137.09072222222224,
    "photos": [
      {
        "src": "https://raw.githubusercontent.com/tmgddjtt57-collab/notomap/main/media/spots/1782795833268-spot-mr06lwtd-o3el8m-7-line-album-20260630-260630-12.jpg?v=1782795836669",
        "alt": "LINE_ALBUM_20260630_260630_12.jpg",
        "path": "media/spots/1782795833268-spot-mr06lwtd-o3el8m-7-line-album-20260630-260630-12.jpg"
      }
    ]
  },
  {
    "id": "spot-mr06lv85-cf7rl8",
    "createdAt": "2026-06-30T05:03:53.184Z",
    "updatedAt": "2026-06-30T05:03:53.184Z",
    "title": {
      "ja": "春は静かに、 昔の時間へと戻っていく。",
      "en": "springは静かに、 昔の時間へと戻っていく。",
      "ko": "봄は静かに、 昔の時間へと戻っていく。",
      "zh": "春天は静かに、 昔の時間へと戻っていく。"
    },
    "description": {
      "ja": "春は静かに、\n昔の時間へと戻っていく。\nSpring quietly\ndrifts back\ntoward an older time.\n\n神和住の枝垂れ桜【The Weeping Cherry Tree in Kamiwasumi】\nNoto Town, Noto Peninsula, Japan\n\n37°20'27.4\"N 137°03'47.8\"E\n\nArchive 008\n#ShinHangaNoto\n#InspiredByShoenUemura\n#InspiredByKawaseHasui\n#NotoTown\n#NotoNoOtoMuseum",
      "en": "春は静かに、\n昔の時間へと戻っていく。\nSpring quietly\ndrifts back\ntoward an older time.\n\n神和住の枝垂れ桜【The Weeping Cherry Tree in Kamiwasumi】\nNoto Town, Noto Peninsula, Japan\n\n37°20'27.4\"N 137°03'47.8\"E\n\nArchive 008\n#ShinHangaNoto\n#InspiredByShoenUemura\n#InspiredByKawaseHasui\n#NotoTown\n#NotoNoOtoMuseum",
      "ko": "봄は静かに、\n昔の時間へと戻っていく。\nSpring quietly\ndrifts back\ntoward an older time.\n\n神和住の枝垂れ桜【The Weeping Cherry Tree in Kamiwasumi】\n노토마치, Noto Peninsula, Japan\n\n37°20'27.4\"N 137°03'47.8\"E\n\nArchive 008\n#ShinHangaNoto\n#InspiredByShoenUemura\n#InspiredByKawaseHasui\n#NotoTown\n#NotoNoOtoMuseum",
      "zh": "春天は静かに、\n昔の時間へと戻っていく。\nSpring quietly\ndrifts back\ntoward an older time.\n\n神和住の枝垂れ桜【The Weeping Cherry Tree in Kamiwasumi】\n能登町, Noto Peninsula, Japan\n\n37°20'27.4\"N 137°03'47.8\"E\n\nArchive 008\n#ShinHangaNoto\n#InspiredByShoenUemura\n#InspiredByKawaseHasui\n#NotoTown\n#NotoNoOtoMuseum"
    },
    "municipality": {
      "ja": "能登町",
      "en": "Noto Town",
      "ko": "노토마치",
      "zh": "能登町"
    },
    "group": "能登町",
    "locationText": "37°20'27.4\"N 137°03'47.8\"E",
    "lat": 37.340944444444446,
    "lng": 137.06327777777778,
    "photos": [
      {
        "src": "https://raw.githubusercontent.com/tmgddjtt57-collab/notomap/main/media/spots/1782795831218-spot-mr06lv85-cf7rl8-6-line-album-20260630-260630-11.jpg?v=1782795833184",
        "alt": "LINE_ALBUM_20260630_260630_11.jpg",
        "path": "media/spots/1782795831218-spot-mr06lv85-cf7rl8-6-line-album-20260630-260630-11.jpg"
      }
    ]
  },
  {
    "id": "spot-mr06ltvl-ywl5pl",
    "createdAt": "2026-06-30T05:03:51.124Z",
    "updatedAt": "2026-06-30T05:03:51.124Z",
    "title": {
      "ja": "街は静かに、 まだ昨日の続きを見ている。",
      "en": "街は静かに、 まだ昨日の続きを見ている。",
      "ko": "街は静かに、 まだ昨日の続きを見ている。",
      "zh": "街は静かに、 まだ昨日の続きを見ている。"
    },
    "description": {
      "ja": "街は静かに、\nまだ昨日の続きを見ている。\nThe city remains quiet,\nstill watching\nyesterday continue.\n\n輪島市遠望【View from Wajima City Hall】\nWajima, Noto Peninsula, Japan\n\n37°23’26.9”N 136°53’57.3”E\n\nArchive 007\n#RealismNoto\n#InspiredByRyuseiKishida\n#InspiredByEdwardHopper\n#WajimaCity\n#NotoNoOtoMuseum",
      "en": "街は静かに、\nまだ昨日の続きを見ている。\nThe city remains quiet,\nstill watching\nyesterday continue.\n\n輪島市遠望【View from Wajima City Hall】\nWajima, Noto Peninsula, Japan\n\n37°23’26.9”N 136°53’57.3”E\n\nArchive 007\n#RealismNoto\n#InspiredByRyuseiKishida\n#InspiredByEdwardHopper\n#WajimaCity\n#NotoNoOtoMuseum",
      "ko": "街は静かに、\nまだ昨日の続きを見ている。\nThe city remains quiet,\nstill watching\nyesterday continue.\n\n와지마시遠望【View from 와지마시 City Hall】\n와지마시, Noto Peninsula, Japan\n\n37°23’26.9”N 136°53’57.3”E\n\nArchive 007\n#RealismNoto\n#InspiredByRyuseiKishida\n#InspiredByEdwardHopper\n#와지마시City\n#NotoNoOtoMuseum",
      "zh": "街は静かに、\nまだ昨日の続きを見ている。\nThe city remains quiet,\nstill watching\nyesterday continue.\n\n轮岛市遠望【View from 轮岛市 City Hall】\n轮岛市, Noto Peninsula, Japan\n\n37°23’26.9”N 136°53’57.3”E\n\nArchive 007\n#RealismNoto\n#InspiredByRyuseiKishida\n#InspiredByEdwardHopper\n#轮岛市City\n#NotoNoOtoMuseum"
    },
    "municipality": {
      "ja": "輪島市",
      "en": "Wajima",
      "ko": "와지마시",
      "zh": "轮岛市"
    },
    "group": "輪島市",
    "locationText": "37°23’26.9”N 136°53’57.3”E",
    "lat": 0,
    "lng": 0,
    "photos": [
      {
        "src": "https://raw.githubusercontent.com/tmgddjtt57-collab/notomap/main/media/spots/1782795829427-spot-mr06ltvl-ywl5pl-5-line-album-20260630-260630-10.jpg?v=1782795831124",
        "alt": "LINE_ALBUM_20260630_260630_10.jpg",
        "path": "media/spots/1782795829427-spot-mr06ltvl-ywl5pl-5-line-album-20260630-260630-10.jpg"
      }
    ]
  },
  {
    "id": "spot-mr06lsay-58d5jd",
    "createdAt": "2026-06-30T05:03:49.377Z",
    "updatedAt": "2026-06-30T05:03:49.377Z",
    "title": {
      "ja": "街は静かに、 まだ昨日の続きを見ている。",
      "en": "街は静かに、 まだ昨日の続きを見ている。",
      "ko": "街は静かに、 まだ昨日の続きを見ている。",
      "zh": "街は静かに、 まだ昨日の続きを見ている。"
    },
    "description": {
      "ja": "街は静かに、\nまだ昨日の続きを見ている。\nThe city remains quiet,\nstill watching\nyesterday continue.\n\n輪島市遠望【View from Wajima City Hall】\nWajima, Noto Peninsula, Japan\n\n37°23’26.9”N 136°53’57.3”E\n\nArchive 007\n#RealismNoto\n#InspiredByRyuseiKishida\n#InspiredByEdwardHopper\n#WajimaCity\n#NotoNoOtoMuseum",
      "en": "街は静かに、\nまだ昨日の続きを見ている。\nThe city remains quiet,\nstill watching\nyesterday continue.\n\n輪島市遠望【View from Wajima City Hall】\nWajima, Noto Peninsula, Japan\n\n37°23’26.9”N 136°53’57.3”E\n\nArchive 007\n#RealismNoto\n#InspiredByRyuseiKishida\n#InspiredByEdwardHopper\n#WajimaCity\n#NotoNoOtoMuseum",
      "ko": "街は静かに、\nまだ昨日の続きを見ている。\nThe city remains quiet,\nstill watching\nyesterday continue.\n\n와지마시遠望【View from 와지마시 City Hall】\n와지마시, Noto Peninsula, Japan\n\n37°23’26.9”N 136°53’57.3”E\n\nArchive 007\n#RealismNoto\n#InspiredByRyuseiKishida\n#InspiredByEdwardHopper\n#와지마시City\n#NotoNoOtoMuseum",
      "zh": "街は静かに、\nまだ昨日の続きを見ている。\nThe city remains quiet,\nstill watching\nyesterday continue.\n\n轮岛市遠望【View from 轮岛市 City Hall】\n轮岛市, Noto Peninsula, Japan\n\n37°23’26.9”N 136°53’57.3”E\n\nArchive 007\n#RealismNoto\n#InspiredByRyuseiKishida\n#InspiredByEdwardHopper\n#轮岛市City\n#NotoNoOtoMuseum"
    },
    "municipality": {
      "ja": "輪島市",
      "en": "Wajima",
      "ko": "와지마시",
      "zh": "轮岛市"
    },
    "group": "輪島市",
    "locationText": "37°23’26.9”N 136°53’57.3”E",
    "lat": 0,
    "lng": 0,
    "photos": [
      {
        "src": "https://raw.githubusercontent.com/tmgddjtt57-collab/notomap/main/media/spots/1782795827472-spot-mr06lsay-58d5jd-4-line-album-20260630-260630-9.jpg?v=1782795829377",
        "alt": "LINE_ALBUM_20260630_260630_9.jpg",
        "path": "media/spots/1782795827472-spot-mr06lsay-58d5jd-4-line-album-20260630-260630-9.jpg"
      }
    ]
  },
  {
    "id": "spot-mr06lq3l-af20ya",
    "createdAt": "2026-06-30T05:03:47.337Z",
    "updatedAt": "2026-06-30T05:03:47.337Z",
    "title": {
      "ja": "海の色が、 空まで続いていた。",
      "en": "seaの色が、 空まで続いていた。",
      "ko": "바다の色が、 空まで続いていた。",
      "zh": "海の色が、 空まで続いていた。"
    },
    "description": {
      "ja": "海の色が、\n空まで続いていた。\nThe color of the sea\nkept continuing\ninto the sky.\n\n羽根八幡神社【Hane Hachiman Shrine】\nNoto Town, Noto Peninsula, Japan\n\n37°18’04.9”N 137°10’35.7”E\n\nArchive 010\n#NeoImpressionismNoto\n#InspiredBySeurat\n#InspiredByMillet\n#NotoTown\n#NotoNoOtoMuseum",
      "en": "海の色が、\n空まで続いていた。\nThe color of the sea\nkept continuing\ninto the sky.\n\n羽根八幡神社【Hane Hachiman Shrine】\nNoto Town, Noto Peninsula, Japan\n\n37°18’04.9”N 137°10’35.7”E\n\nArchive 010\n#NeoImpressionismNoto\n#InspiredBySeurat\n#InspiredByMillet\n#NotoTown\n#NotoNoOtoMuseum",
      "ko": "바다の色が、\n空まで続いていた。\nThe color of the sea\nkept continuing\ninto the sky.\n\n羽根八幡神社【Hane Hachiman Shrine】\n노토마치, Noto Peninsula, Japan\n\n37°18’04.9”N 137°10’35.7”E\n\nArchive 010\n#NeoImpressionismNoto\n#InspiredBySeurat\n#InspiredByMillet\n#NotoTown\n#NotoNoOtoMuseum",
      "zh": "海の色が、\n空まで続いていた。\nThe color of the sea\nkept continuing\ninto the sky.\n\n羽根八幡神社【Hane Hachiman Shrine】\n能登町, Noto Peninsula, Japan\n\n37°18’04.9”N 137°10’35.7”E\n\nArchive 010\n#NeoImpressionismNoto\n#InspiredBySeurat\n#InspiredByMillet\n#NotoTown\n#NotoNoOtoMuseum"
    },
    "municipality": {
      "ja": "能登町",
      "en": "Noto Town",
      "ko": "노토마치",
      "zh": "能登町"
    },
    "group": "能登町",
    "locationText": "37°18’04.9”N 137°10’35.7”E",
    "lat": 0,
    "lng": 0,
    "photos": [
      {
        "src": "https://raw.githubusercontent.com/tmgddjtt57-collab/notomap/main/media/spots/1782795824556-spot-mr06lq3l-af20ya-3-line-album-20260630-260630-8.jpg?v=1782795827337",
        "alt": "LINE_ALBUM_20260630_260630_8.jpg",
        "path": "media/spots/1782795824556-spot-mr06lq3l-af20ya-3-line-album-20260630-260630-8.jpg"
      }
    ]
  },
  {
    "id": "spot-mr06lofy-59bn83",
    "createdAt": "2026-06-30T05:03:44.481Z",
    "updatedAt": "2026-06-30T05:03:44.481Z",
    "title": {
      "ja": "……妙だな。 さっきから、空気が ずっと重い。",
      "en": "……妙だな。 さっきから、空気が ずっと重い。",
      "ko": "……妙だな。 さっきから、空気が ずっと重い。",
      "zh": "……妙だな。 さっきから、空気が ずっと重い。"
    },
    "description": {
      "ja": "……妙だな。\nさっきから、空気が\nずっと重い。\n...Strange.\nThe air’s been heavy\nthis whole time.\n\n實相寺【Jissoji Temple】\nNanao, Noto Peninsula, Japan\n\n37°03’00.7”N 136°57’11.8”E\n\nArchive 016\n#ExpressionismNoto\n#InspiredByJoJosBizarreAdventure\n#NanaoCity\n#NotoNoOtoMuseum",
      "en": "……妙だな。\nさっきから、空気が\nずっと重い。\n...Strange.\nThe air’s been heavy\nthis whole time.\n\n實相寺【Jissoji Temple】\nNanao, Noto Peninsula, Japan\n\n37°03’00.7”N 136°57’11.8”E\n\nArchive 016\n#ExpressionismNoto\n#InspiredByJoJosBizarreAdventure\n#NanaoCity\n#NotoNoOtoMuseum",
      "ko": "……妙だな。\nさっきから、空気が\nずっと重い。\n...Strange.\nThe air’s been heavy\nthis whole time.\n\n實相寺【Jissoji Temple】\n나나오시, Noto Peninsula, Japan\n\n37°03’00.7”N 136°57’11.8”E\n\nArchive 016\n#ExpressionismNoto\n#InspiredByJoJosBizarreAdventure\n#나나오시City\n#NotoNoOtoMuseum",
      "zh": "……妙だな。\nさっきから、空気が\nずっと重い。\n...Strange.\nThe air’s been heavy\nthis whole time.\n\n實相寺【Jissoji Temple】\n七尾市, Noto Peninsula, Japan\n\n37°03’00.7”N 136°57’11.8”E\n\nArchive 016\n#ExpressionismNoto\n#InspiredByJoJosBizarreAdventure\n#七尾市City\n#NotoNoOtoMuseum"
    },
    "municipality": {
      "ja": "七尾市",
      "en": "Nanao",
      "ko": "나나오시",
      "zh": "七尾市"
    },
    "group": "七尾市",
    "locationText": "37°03’00.7”N 136°57’11.8”E",
    "lat": 0,
    "lng": 0,
    "photos": [
      {
        "src": "https://raw.githubusercontent.com/tmgddjtt57-collab/notomap/main/media/spots/1782795822426-spot-mr06lofy-59bn83-2-line-album-20260630-260630-20.jpg?v=1782795824481",
        "alt": "LINE_ALBUM_20260630_260630_20.jpg",
        "path": "media/spots/1782795822426-spot-mr06lofy-59bn83-2-line-album-20260630-260630-20.jpg"
      }
    ]
  },
  {
    "id": "spot-mr06lmzo-gs85am",
    "createdAt": "2026-06-30T05:03:42.332Z",
    "updatedAt": "2026-06-30T05:03:42.332Z",
    "title": {
      "ja": "風が吹くまで、 時間は動かない。",
      "en": "風が吹くまで、 時間は動かない。",
      "ko": "風が吹くまで、 時間は動かない。",
      "zh": "風が吹くまで、 時間は動かない。"
    },
    "description": {
      "ja": "風が吹くまで、\n時間は動かない。\nUntil the wind begins,\ntime will not move.\n\nサンセットウィング内灘\n【Sunset Wing Uchinada】\nUchinada, Ishikawa, Japan\n\n36°39’19.8”N 136°39’11.1”E\n\nArchive 015\n#MetaphysicalNoto\n#InspiredByMetaphysicalArt\n#UchinadaTown\n#NotoNoOtoMuseum",
      "en": "風が吹くまで、\n時間は動かない。\nUntil the wind begins,\ntime will not move.\n\nサンセットウィング内灘\n【Sunset Wing Uchinada】\nUchinada, Ishikawa, Japan\n\n36°39’19.8”N 136°39’11.1”E\n\nArchive 015\n#MetaphysicalNoto\n#InspiredByMetaphysicalArt\n#UchinadaTown\n#NotoNoOtoMuseum",
      "ko": "風が吹くまで、\n時間は動かない。\nUntil the wind begins,\ntime will not move.\n\nサンセットウィング内灘\n【Sunset Wing Uchinada】\nUchinada, I시카마치wa, Japan\n\n36°39’19.8”N 136°39’11.1”E\n\nArchive 015\n#MetaphysicalNoto\n#InspiredByMetaphysicalArt\n#UchinadaTown\n#NotoNoOtoMuseum",
      "zh": "風が吹くまで、\n時間は動かない。\nUntil the wind begins,\ntime will not move.\n\nサンセットウィング内灘\n【Sunset Wing Uchinada】\nUchinada, I志贺町wa, Japan\n\n36°39’19.8”N 136°39’11.1”E\n\nArchive 015\n#MetaphysicalNoto\n#InspiredByMetaphysicalArt\n#UchinadaTown\n#NotoNoOtoMuseum"
    },
    "municipality": {
      "ja": "志賀町",
      "en": "Shika",
      "ko": "시카마치",
      "zh": "志贺町"
    },
    "group": "志賀町",
    "locationText": "36°39’19.8”N 136°39’11.1”E",
    "lat": 0,
    "lng": 0,
    "photos": [
      {
        "src": "https://raw.githubusercontent.com/tmgddjtt57-collab/notomap/main/media/spots/1782795820526-spot-mr06lmzo-gs85am-1-line-album-20260630-260630-19.jpg?v=1782795822332",
        "alt": "LINE_ALBUM_20260630_260630_19.jpg",
        "path": "media/spots/1782795820526-spot-mr06lmzo-gs85am-1-line-album-20260630-260630-19.jpg"
      }
    ]
  },
  {
    "id": "spot-mr06azqe-10bhk8",
    "createdAt": "2026-06-30T04:55:25.771Z",
    "updatedAt": "2026-06-30T04:55:25.771Z",
    "title": {
      "ja": "熊野隧道南口",
      "en": "Kumano Tunnel South Entrance",
      "ko": "熊野隧道南口",
      "zh": "熊野隧道南口"
    },
    "description": {
      "ja": "We are with NOTO\n\n熊野隧道南口【Kumano Tunnel South Entrance】\nWajima, Noto Peninsula, Japan\n\n37°19'58.2\"N 136°53'52.3\"E\n\nArchive 003\n#ExpressionismNoto\n#InspiredByGermanExpressionism\n#InspiredByTangDynasty\n#OuterWajima\n#NotoNoOtoMuseum",
      "en": "We are with NOTO\n\n熊野隧道南口【Kumano Tunnel South Entrance】\nWajima, Noto Peninsula, Japan\n\n37°19'58.2\"N 136°53'52.3\"E\n\nArchive 003\n#ExpressionismNoto\n#InspiredByGermanExpressionism\n#InspiredByTangDynasty\n#OuterWajima\n#NotoNoOtoMuseum",
      "ko": "We are with NOTO\n\n熊野隧道南口【Kumano Tunnel South Entrance】\n와지마시, Noto Peninsula, Japan\n\n37°19'58.2\"N 136°53'52.3\"E\n\nArchive 003\n#ExpressionismNoto\n#InspiredByGermanExpressionism\n#InspiredByTangDynasty\n#Outer와지마시\n#NotoNoOtoMuseum",
      "zh": "We are with NOTO\n\n熊野隧道南口【Kumano Tunnel South Entrance】\n轮岛市, Noto Peninsula, Japan\n\n37°19'58.2\"N 136°53'52.3\"E\n\nArchive 003\n#ExpressionismNoto\n#InspiredByGermanExpressionism\n#InspiredByTangDynasty\n#Outer轮岛市\n#NotoNoOtoMuseum"
    },
    "municipality": {
      "ja": "輪島市",
      "en": "Wajima",
      "ko": "와지마시",
      "zh": "轮岛市"
    },
    "group": "輪島市",
    "locationText": "37°19'58.2\"N 136°53'52.3\"E",
    "lat": 37.33283333333333,
    "lng": 136.8978611111111,
    "photos": [
      {
        "src": "https://raw.githubusercontent.com/tmgddjtt57-collab/notomap/main/media/spots/1782795323897-spot-mr06azqe-10bhk8-5-line-album-20260630-260630-2.jpg?v=1782795325771",
        "alt": "LINE_ALBUM_20260630_260630_2.jpg",
        "path": "media/spots/1782795323897-spot-mr06azqe-10bhk8-5-line-album-20260630-260630-2.jpg"
      }
    ]
  },
  {
    "id": "spot-mr06ay74-7rih5c",
    "createdAt": "2026-06-30T04:55:23.750Z",
    "updatedAt": "2026-06-30T04:55:23.750Z",
    "title": {
      "ja": "面と点が、 押し寄せる。",
      "en": "面と点が、 押し寄せる。",
      "ko": "面と点が、 押し寄せる。",
      "zh": "面と点が、 押し寄せる。"
    },
    "description": {
      "ja": "面と点が、\n押し寄せる。\nPlanes and dots\ncome rushing in.\n\n百楽荘貸切風呂 【【Private Bath at Noto Hyakurakusou】\nNoto Town, Noto Peninsula, Japan\n\n37°18'36.4\"N 137°13'57.1\"E\n\nArchive 004\n#AvantGardeNoto\n#InspiredByPicasso\n#InspiredByYayoiKusama\n#NotoTown\n#NotoNoOtoMuseum",
      "en": "面と点が、\n押し寄せる。\nPlanes and dots\ncome rushing in.\n\n百楽荘貸切風呂 【【Private Bath at Noto Hyakurakusou】\nNoto Town, Noto Peninsula, Japan\n\n37°18'36.4\"N 137°13'57.1\"E\n\nArchive 004\n#AvantGardeNoto\n#InspiredByPicasso\n#InspiredByYayoiKusama\n#NotoTown\n#NotoNoOtoMuseum",
      "ko": "面と点が、\n押し寄せる。\nPlanes and dots\ncome rushing in.\n\n百楽荘貸切風呂 【【Private Bath at Noto Hyakurakusou】\n노토마치, Noto Peninsula, Japan\n\n37°18'36.4\"N 137°13'57.1\"E\n\nArchive 004\n#AvantGardeNoto\n#InspiredByPicasso\n#InspiredByYayoiKusama\n#NotoTown\n#NotoNoOtoMuseum",
      "zh": "面と点が、\n押し寄せる。\nPlanes and dots\ncome rushing in.\n\n百楽荘貸切風呂 【【Private Bath at Noto Hyakurakusou】\n能登町, Noto Peninsula, Japan\n\n37°18'36.4\"N 137°13'57.1\"E\n\nArchive 004\n#AvantGardeNoto\n#InspiredByPicasso\n#InspiredByYayoiKusama\n#NotoTown\n#NotoNoOtoMuseum"
    },
    "municipality": {
      "ja": "能登町",
      "en": "Noto Town",
      "ko": "노토마치",
      "zh": "能登町"
    },
    "group": "能登町",
    "locationText": "37°18'36.4\"N 137°13'57.1\"E",
    "lat": 37.310111111111105,
    "lng": 137.2325277777778,
    "photos": [
      {
        "src": "https://raw.githubusercontent.com/tmgddjtt57-collab/notomap/main/media/spots/1782795321907-spot-mr06ay74-7rih5c-4-line-album-20260630-260630-1.jpg?v=1782795323736",
        "alt": "LINE_ALBUM_20260630_260630_1.jpg",
        "path": "media/spots/1782795321907-spot-mr06ay74-7rih5c-4-line-album-20260630-260630-1.jpg"
      }
    ]
  },
  {
    "id": "spot-mr06awk0-jzypqb",
    "createdAt": "2026-06-30T04:55:21.759Z",
    "updatedAt": "2026-06-30T04:55:21.759Z",
    "title": {
      "ja": "海の色が、 空まで続いていた。",
      "en": "seaの色が、 空まで続いていた。",
      "ko": "바다の色が、 空まで続いていた。",
      "zh": "海の色が、 空まで続いていた。"
    },
    "description": {
      "ja": "海の色が、\n空まで続いていた。\nThe color of the sea\nkept continuing\ninto the sky.\n\n羽根八幡神社【Hane Hachiman Shrine】\nNoto Town, Noto Peninsula, Japan\n\n37°18’04.9”N 137°10’35.7”E\n\nArchive 010\n#NeoImpressionismNoto\n#InspiredBySeurat\n#InspiredByMillet\n#NotoTown\n#NotoNoOtoMuseum",
      "en": "海の色が、\n空まで続いていた。\nThe color of the sea\nkept continuing\ninto the sky.\n\n羽根八幡神社【Hane Hachiman Shrine】\nNoto Town, Noto Peninsula, Japan\n\n37°18’04.9”N 137°10’35.7”E\n\nArchive 010\n#NeoImpressionismNoto\n#InspiredBySeurat\n#InspiredByMillet\n#NotoTown\n#NotoNoOtoMuseum",
      "ko": "바다の色が、\n空まで続いていた。\nThe color of the sea\nkept continuing\ninto the sky.\n\n羽根八幡神社【Hane Hachiman Shrine】\n노토마치, Noto Peninsula, Japan\n\n37°18’04.9”N 137°10’35.7”E\n\nArchive 010\n#NeoImpressionismNoto\n#InspiredBySeurat\n#InspiredByMillet\n#NotoTown\n#NotoNoOtoMuseum",
      "zh": "海の色が、\n空まで続いていた。\nThe color of the sea\nkept continuing\ninto the sky.\n\n羽根八幡神社【Hane Hachiman Shrine】\n能登町, Noto Peninsula, Japan\n\n37°18’04.9”N 137°10’35.7”E\n\nArchive 010\n#NeoImpressionismNoto\n#InspiredBySeurat\n#InspiredByMillet\n#NotoTown\n#NotoNoOtoMuseum"
    },
    "municipality": {
      "ja": "能登町",
      "en": "Noto Town",
      "ko": "노토마치",
      "zh": "能登町"
    },
    "group": "能登町",
    "locationText": "37°18’04.9”N 137°10’35.7”E",
    "lat": 0,
    "lng": 0,
    "photos": [
      {
        "src": "https://raw.githubusercontent.com/tmgddjtt57-collab/notomap/main/media/spots/1782795319801-spot-mr06awk0-jzypqb-3-line-album-20260630-260630-7.jpg?v=1782795321759",
        "alt": "LINE_ALBUM_20260630_260630_7.jpg",
        "path": "media/spots/1782795319801-spot-mr06awk0-jzypqb-3-line-album-20260630-260630-7.jpg"
      }
    ]
  },
  {
    "id": "spot-mr06aur6-ki8adw",
    "createdAt": "2026-06-30T04:55:19.632Z",
    "updatedAt": "2026-06-30T04:55:19.632Z",
    "title": {
      "ja": "ベンチが、 帰りを、 待っていた。",
      "en": "ベンチが、 帰りを、 待っていた。",
      "ko": "ベンチが、 帰りを、 待っていた。",
      "zh": "ベンチが、 帰りを、 待っていた。"
    },
    "description": {
      "ja": "ベンチが、\n帰りを、\n待っていた。\nThe bench\nwas waiting\nfor return.\n\n大沢集落の間垣【The Magaki Fence in the Osawa Hamlet】\nWajima, Noto Peninsula, Japan\n\n37°22'33.1\"N 136°48'05.0\"E\n\nArchive 006\n#AbstractExpressionismNoto\n#InspiredByJacksonPollock\n#InspiredByJapaneseMingei\n#OuterWajima\n#NotoNoOtoMuseum",
      "en": "ベンチが、\n帰りを、\n待っていた。\nThe bench\nwas waiting\nfor return.\n\n大沢集落の間垣【The Magaki Fence in the Osawa Hamlet】\nWajima, Noto Peninsula, Japan\n\n37°22'33.1\"N 136°48'05.0\"E\n\nArchive 006\n#AbstractExpressionismNoto\n#InspiredByJacksonPollock\n#InspiredByJapaneseMingei\n#OuterWajima\n#NotoNoOtoMuseum",
      "ko": "ベンチが、\n帰りを、\n待っていた。\nThe bench\nwas waiting\nfor return.\n\n大沢集落の間垣【The Magaki Fence in the Osawa Hamlet】\n와지마시, Noto Peninsula, Japan\n\n37°22'33.1\"N 136°48'05.0\"E\n\nArchive 006\n#AbstractExpressionismNoto\n#InspiredByJacksonPollock\n#InspiredByJapaneseMingei\n#Outer와지마시\n#NotoNoOtoMuseum",
      "zh": "ベンチが、\n帰りを、\n待っていた。\nThe bench\nwas waiting\nfor return.\n\n大沢集落の間垣【The Magaki Fence in the Osawa Hamlet】\n轮岛市, Noto Peninsula, Japan\n\n37°22'33.1\"N 136°48'05.0\"E\n\nArchive 006\n#AbstractExpressionismNoto\n#InspiredByJacksonPollock\n#InspiredByJapaneseMingei\n#Outer轮岛市\n#NotoNoOtoMuseum"
    },
    "municipality": {
      "ja": "輪島市",
      "en": "Wajima",
      "ko": "와지마시",
      "zh": "轮岛市"
    },
    "group": "輪島市",
    "locationText": "37°22'33.1\"N 136°48'05.0\"E",
    "lat": 37.375861111111114,
    "lng": 136.8013888888889,
    "photos": [
      {
        "src": "https://raw.githubusercontent.com/tmgddjtt57-collab/notomap/main/media/spots/1782795317444-spot-mr06aur6-ki8adw-2-line-album-20260630-260630-6.jpg?v=1782795319632",
        "alt": "LINE_ALBUM_20260630_260630_6.jpg",
        "path": "media/spots/1782795317444-spot-mr06aur6-ki8adw-2-line-album-20260630-260630-6.jpg"
      }
    ]
  },
  {
    "id": "spot-mr06at82-m0mh8d",
    "createdAt": "2026-06-30T04:55:17.297Z",
    "updatedAt": "2026-06-30T04:55:17.297Z",
    "title": {
      "ja": "ベンチが、 帰りを、 待っていた。",
      "en": "ベンチが、 帰りを、 待っていた。",
      "ko": "ベンチが、 帰りを、 待っていた。",
      "zh": "ベンチが、 帰りを、 待っていた。"
    },
    "description": {
      "ja": "ベンチが、\n帰りを、\n待っていた。\nThe bench\nwas waiting\nfor return.\n\n大沢集落の間垣【The Magaki Fence in the Osawa Hamlet】\nWajima, Noto Peninsula, Japan\n\n37°22'33.1\"N 136°48'05.0\"E\n\nArchive 006\n#AbstractExpressionismNoto\n#InspiredByJacksonPollock\n#InspiredByJapaneseMingei\n#OuterWajima\n#NotoNoOtoMuseum",
      "en": "ベンチが、\n帰りを、\n待っていた。\nThe bench\nwas waiting\nfor return.\n\n大沢集落の間垣【The Magaki Fence in the Osawa Hamlet】\nWajima, Noto Peninsula, Japan\n\n37°22'33.1\"N 136°48'05.0\"E\n\nArchive 006\n#AbstractExpressionismNoto\n#InspiredByJacksonPollock\n#InspiredByJapaneseMingei\n#OuterWajima\n#NotoNoOtoMuseum",
      "ko": "ベンチが、\n帰りを、\n待っていた。\nThe bench\nwas waiting\nfor return.\n\n大沢集落の間垣【The Magaki Fence in the Osawa Hamlet】\n와지마시, Noto Peninsula, Japan\n\n37°22'33.1\"N 136°48'05.0\"E\n\nArchive 006\n#AbstractExpressionismNoto\n#InspiredByJacksonPollock\n#InspiredByJapaneseMingei\n#Outer와지마시\n#NotoNoOtoMuseum",
      "zh": "ベンチが、\n帰りを、\n待っていた。\nThe bench\nwas waiting\nfor return.\n\n大沢集落の間垣【The Magaki Fence in the Osawa Hamlet】\n轮岛市, Noto Peninsula, Japan\n\n37°22'33.1\"N 136°48'05.0\"E\n\nArchive 006\n#AbstractExpressionismNoto\n#InspiredByJacksonPollock\n#InspiredByJapaneseMingei\n#Outer轮岛市\n#NotoNoOtoMuseum"
    },
    "municipality": {
      "ja": "輪島市",
      "en": "Wajima",
      "ko": "와지마시",
      "zh": "轮岛市"
    },
    "group": "輪島市",
    "locationText": "37°22'33.1\"N 136°48'05.0\"E",
    "lat": 37.375861111111114,
    "lng": 136.8013888888889,
    "photos": [
      {
        "src": "https://raw.githubusercontent.com/tmgddjtt57-collab/notomap/main/media/spots/1782795315394-spot-mr06at82-m0mh8d-1-line-album-20260630-260630-5.jpg?v=1782795317297",
        "alt": "LINE_ALBUM_20260630_260630_5.jpg",
        "path": "media/spots/1782795315394-spot-mr06at82-m0mh8d-1-line-album-20260630-260630-5.jpg"
      }
    ]
  },
  {
    "id": "spot-mqzfm87a-l8ox6u",
    "createdAt": "2026-06-29T16:28:20.616Z",
    "updatedAt": "2026-06-30T00:00:00.000Z",
    "title": {
      "ja": "貴廟の水芭蕉",
      "en": "Kibyo Area / Asian skunk cabbage",
      "ko": "기뵤 지역 / 물파초",
      "zh": "贵庙地区 / 水芭蕉"
    },
    "description": {
      "ja": "Reimagining the spring landscapes of Noto\nthrough the color language of Impressionism,\nwith particular inspiration drawn from Monet’s treatment of light.",
      "en": "Reimagining the spring landscapes of Noto\nthrough the color language of Impressionism,\nwith particular inspiration drawn from Monet’s treatment of light.",
      "ko": "인상주의의 색채 언어로 노토의 봄 풍경을 재해석하며, 특히 모네의 빛 표현에서 영감을 받았습니다.",
      "zh": "以印象派的色彩语言重新想象能登的春日风景，尤其受到莫奈对光线处理方式的启发。"
    },
    "municipality": {
      "ja": "輪島市",
      "en": "Wajima",
      "ko": "와지마시",
      "zh": "轮岛市"
    },
    "group": "輪島市",
    "locationText": "37°21'45.3\"N 136°50'21.1\"E",
    "lat": 37.36258333333333,
    "lng": 136.83919444444444,
    "photos": [
      {
        "src": "https://raw.githubusercontent.com/tmgddjtt57-collab/notomap/main/media/spots/1782750498398-spot-mqzfm87a-l8ox6u-1-02adc532-2ee9-4f5c-932e-ab54714fec8a.jpg?v=1782750500616",
        "alt": "02ADC532-2EE9-4F5C-932E-AB54714FEC8A.png",
        "path": "media/spots/1782750498398-spot-mqzfm87a-l8ox6u-1-02adc532-2ee9-4f5c-932e-ab54714fec8a.jpg"
      }
    ]
  },
  {
    "id": "spot-mqzgk3ic-vjm9vn",
    "createdAt": "2026-06-29T16:54:40.644Z",
    "updatedAt": "2026-06-29T16:54:40.644Z",
    "title": {
      "ja": "熊野隧道南口",
      "en": "Kumano Tunnel South Entrance",
      "ko": "熊野隧道南口",
      "zh": "熊野隧道南口"
    },
    "description": {
      "ja": "熊野隧道南口【Kumano Tunnel South Entrance】\nWajima, Noto Peninsula, Japan\n\n37°19'58.2\"N 136°53'52.3\"E\n\nArchive 003\n#ExpressionismNoto\n#InspiredByGermanExpressionism\n#InspiredByTangDynasty\n#OuterWajima\n#NotoNoOtoMuseum",
      "en": "熊野隧道南口【Kumano Tunnel South Entrance】\nWajima, Noto Peninsula, Japan\n\n37°19'58.2\"N 136°53'52.3\"E\n\nArchive 003\n#ExpressionismNoto\n#InspiredByGermanExpressionism\n#InspiredByTangDynasty\n#OuterWajima\n#NotoNoOtoMuseum",
      "ko": "熊野隧道南口【Kumano Tunnel South Entrance】\n와지마시, Noto Peninsula, Japan\n\n37°19'58.2\"N 136°53'52.3\"E\n\nArchive 003\n#ExpressionismNoto\n#InspiredByGermanExpressionism\n#InspiredByTangDynasty\n#Outer와지마시\n#NotoNoOtoMuseum",
      "zh": "熊野隧道南口【Kumano Tunnel South Entrance】\n轮岛市, Noto Peninsula, Japan\n\n37°19'58.2\"N 136°53'52.3\"E\n\nArchive 003\n#ExpressionismNoto\n#InspiredByGermanExpressionism\n#InspiredByTangDynasty\n#Outer轮岛市\n#NotoNoOtoMuseum"
    },
    "municipality": {
      "ja": "輪島市",
      "en": "Wajima",
      "ko": "와지마시",
      "zh": "轮岛市"
    },
    "group": "輪島市",
    "locationText": "37°19'58.2\"N 136°53'52.3\"E",
    "lat": 37.33283333333333,
    "lng": 136.8978611111111,
    "photos": [
      {
        "src": "https://raw.githubusercontent.com/tmgddjtt57-collab/notomap/main/media/spots/1782752078638-spot-mqzgk3ic-vjm9vn-2-90bb9b09-8f68-4b2e-90fe-58d723a08bf0.jpg?v=1782752080644",
        "alt": "90BB9B09-8F68-4B2E-90FE-58D723A08BF0.png",
        "path": "media/spots/1782752078638-spot-mqzgk3ic-vjm9vn-2-90bb9b09-8f68-4b2e-90fe-58d723a08bf0.jpg"
      }
    ]
  },
  {
    "id": "spot-mqzgk1e7-n9b27a",
    "createdAt": "2026-06-29T16:54:38.532Z",
    "updatedAt": "2026-06-29T16:54:38.532Z",
    "title": {
      "ja": "古城が、 揺らめいていた。",
      "en": "古城が、 揺らめいていた。",
      "ko": "古城が、 揺らめいていた。",
      "zh": "古城が、 揺らめいていた。"
    },
    "description": {
      "ja": "古城が、\n揺らめいていた。\nThe old castle\nseemed to flicker.\n\n七尾城本丸跡【Nanao Castle Site｜Main Bailey Area】\nNanao, Noto Peninsula, Japan\n\n37°00'32.3\"N 136°59'03.1\"E\n\nArchive 002\n#ExpressionismNoto\n#InspiredByMunch\n#NanaoCity\n#NotoNoOtoMuseum",
      "en": "古城が、\n揺らめいていた。\nThe old castle\nseemed to flicker.\n\n七尾城本丸跡【Nanao Castle Site｜Main Bailey Area】\nNanao, Noto Peninsula, Japan\n\n37°00'32.3\"N 136°59'03.1\"E\n\nArchive 002\n#ExpressionismNoto\n#InspiredByMunch\n#NanaoCity\n#NotoNoOtoMuseum",
      "ko": "古城が、\n揺らめいていた。\nThe old castle\nseemed to flicker.\n\n나나오시城本丸跡【나나오시 Castle Site｜Main Bailey Area】\n나나오시, Noto Peninsula, Japan\n\n37°00'32.3\"N 136°59'03.1\"E\n\nArchive 002\n#ExpressionismNoto\n#InspiredByMunch\n#나나오시City\n#NotoNoOtoMuseum",
      "zh": "古城が、\n揺らめいていた。\nThe old castle\nseemed to flicker.\n\n七尾市城本丸跡【七尾市 Castle Site｜Main Bailey Area】\n七尾市, Noto Peninsula, Japan\n\n37°00'32.3\"N 136°59'03.1\"E\n\nArchive 002\n#ExpressionismNoto\n#InspiredByMunch\n#七尾市City\n#NotoNoOtoMuseum"
    },
    "municipality": {
      "ja": "七尾市",
      "en": "Nanao",
      "ko": "나나오시",
      "zh": "七尾市"
    },
    "group": "七尾市",
    "locationText": "37°00'32.3\"N 136°59'03.1\"E",
    "lat": 37.00897222222222,
    "lng": 136.98419444444443,
    "photos": [
      {
        "src": "https://raw.githubusercontent.com/tmgddjtt57-collab/notomap/main/media/spots/1782752075872-spot-mqzgk1e7-n9b27a-1-b29e6824-3317-4cd6-8435-7be864ca5207.jpg?v=1782752078532",
        "alt": "B29E6824-3317-4CD6-8435-7BE864CA5207.png",
        "path": "media/spots/1782752075872-spot-mqzgk1e7-n9b27a-1-b29e6824-3317-4cd6-8435-7be864ca5207.jpg"
      }
    ]
  }
]
